UDP/Client.py
UDP/Sever.py
UDP/__init__.py
core/Event.py
core/Gui.py
core/Main.py
core/Router.py
core/RouterList.py
core/ThreadPool.py
core/Tools.py
core/__init__.py
zrip-1.4.dist-info/METADATA
zrip-1.4.dist-info/WHEEL
zrip-1.4.dist-info/entry_points.txt
zrip-1.4.dist-info/top_level.txt
zrip-1.4.dist-info/RECORD
