Metadata-Version: 2.1
Name: zrip
Version: 1.4
Summary: rip
Home-page: https://github.com/zcdzcdzcd
Author: zengcd
Author-email: zcd0712@gmail.com
License: UNKNOWN
Platform: UNKNOWN
Requires-Python: >=3.7
Requires-Dist: matplotlib (==3.0.3)
Requires-Dist: networkx (==2.2)
Requires-Dist: setuptools (==41.2.0)
Requires-Dist: Pillow (==6.2.1)
